inprint/__init__.py
inprint/colours.py
inprint/functions.py
inprint-1.1.2.dist-info/LICENSE
inprint-1.1.2.dist-info/METADATA
inprint-1.1.2.dist-info/WHEEL
inprint-1.1.2.dist-info/top_level.txt
inprint-1.1.2.dist-info/RECORD
